aioredis_watchdog/__init__.py
aioredis_watchdog/__main__.py
aioredis_watchdog/watchdog.py
aioredis_watchdog-0.0.4.dist-info/METADATA
aioredis_watchdog-0.0.4.dist-info/WHEEL
aioredis_watchdog-0.0.4.dist-info/entry_points.txt
aioredis_watchdog-0.0.4.dist-info/top_level.txt
aioredis_watchdog-0.0.4.dist-info/RECORD
